ididi/__init__.py
ididi/_ds.py
ididi/_node.py
ididi/_type_resolve.py
ididi/api.py
ididi/config.py
ididi/errors.py
ididi/graph.py
ididi/interfaces.py
ididi/py.typed
ididi/tool.py
ididi/visual.py
ididi/utils/__init__.py
ididi/utils/param_utils.py
ididi/utils/typing_utils.py
ididi-1.8.4.dist-info/METADATA
ididi-1.8.4.dist-info/WHEEL
ididi-1.8.4.dist-info/licenses/LICENSE
ididi-1.8.4.dist-info/RECORD
