Metadata-Version: 2.4
Name: ididi
Version: 1.8.4
Summary: A dependency injection library for Python, Optimized for serverless applications
Author-email: raceychan <raceychan@gmail.com>
License-File: LICENSE
Classifier: Development Status :: 5 - Production/Stable
Classifier: Intended Audience :: Developers
Classifier: Intended Audience :: Information Technology
Classifier: Intended Audience :: System Administrators
Classifier: License :: OSI Approved :: MIT License
Classifier: Programming Language :: Python :: 3 :: Only
Classifier: Programming Language :: Python :: 3.9
Classifier: Programming Language :: Python :: 3.10
Classifier: Programming Language :: Python :: 3.11
Classifier: Programming Language :: Python :: 3.12
Classifier: Programming Language :: Python :: 3.13
Classifier: Topic :: Software Development :: Libraries :: Python Modules
Requires-Python: >=3.9
Requires-Dist: typing-extensions
Provides-Extra: graphviz
Requires-Dist: python-graphviz<0.21,>=0.20.3; extra == 'graphviz'
